[{
    "name": "Sw J1644+57",
    "ra": [
        {
            "value": "16 44 49.93130",
	    "source": "1"
        }
    ],
    "dec": [
        {
            "value": "+57 34 59.6893",
	    "source": "1"
        }
    ],
    "z": [
        {
            "value": "0.354"
        }
    ],
    "nu_GHz": [
        {
            "value": "4.9"
        }
    ],
    "aliases": [
        {
            "value": "Sw J16644+57"
        }
    ],
    "upperlimit": [
        {
            "value": "False"
        }
    ],
    "sources": [
        {
            "name": "Zauderer et al. (2011)",
            "bibcode": "2011Natur.476..425Z",
            "alias": "1"
        },
        {
            "name": "Berger et al. (2012)",
            "bibcode": "2012ApJ...748...36B",
            "alias": "2"
        },
        {
            "name": "Wiersema et al. (2012)",
            "bibcode": "2012MNRAS.421.1942W",
            "alias": "3"
        },
        {
            "name": "Zauderer et al. (2013)",
            "bibcode": "2013ApJ...767..152Z",
            "alias": "4"
        },
        {
            "name": "Yang et al. (2016)",
            "bibcode": "2016MNRAS.462L..66Y",
            "alias": "5"
        },
        {
            "name": "Eftekhari et al. (2018)",
            "bibcode": "2018ApJ...854...86E",
            "alias": "6"
        }
    ],
    "photometry": {
        "radio": [
            {
                "t_MJD": null,
                "t_disc": null,
                "dt_days": 3.87,
                "dt_years": 0.0106027397,
                "F_mJy": 0.25,
                "luminosity": 3.369687649e+39,
                "time": 3.87,
                "source": "unknown"
            },
            {
                "t_MJD": null,
                "t_disc": null,
                "dt_days": 4.76,
                "dt_years": 0.0130410959,
                "F_mJy": 0.34,
                "luminosity": 4.582775202e+39,
                "time": 4.76,
                "source": "unknown"
            },
            {
                "t_MJD": null,
                "t_disc": null,
                "dt_days": 5.0,
                "dt_years": 0.0136986301,
                "F_mJy": 0.34,
                "luminosity": 4.582775202e+39,
                "time": 5.0,
                "source": "unknown"
            },
            {
                "t_MJD": null,
                "t_disc": null,
                "dt_days": 5.79,
                "dt_years": 0.0158630137,
                "F_mJy": 0.61,
                "luminosity": 8.222037863e+39,
                "time": 5.79,
                "source": "unknown"
            },
            {
                "t_MJD": null,
                "t_disc": null,
                "dt_days": 6.78,
                "dt_years": 0.0185753425,
                "F_mJy": 0.82,
                "luminosity": 1.105257549e+40,
                "time": 6.78,
                "source": "unknown"
            },
            {
                "t_MJD": null,
                "t_disc": null,
                "dt_days": 7.77,
                "dt_years": 0.0212876712,
                "F_mJy": 1.48,
                "luminosity": 1.994855088e+40,
                "time": 7.77,
                "source": "unknown"
            },
            {
                "t_MJD": null,
                "t_disc": null,
                "dt_days": 9.79,
                "dt_years": 0.0268219178,
                "F_mJy": 1.47,
                "luminosity": 1.981376337e+40,
                "time": 9.79,
                "source": "unknown"
            },
            {
                "t_MJD": null,
                "t_disc": null,
                "dt_days": 14.98,
                "dt_years": 0.0410410959,
                "F_mJy": 1.8,
                "luminosity": 2.426175107e+40,
                "time": 14.98,
                "source": "unknown"
            },
            {
                "t_MJD": null,
                "t_disc": null,
                "dt_days": 22.78,
                "dt_years": 0.0624109589,
                "F_mJy": 2.1,
                "luminosity": 2.830537625e+40,
                "time": 22.78,
                "source": "unknown"
            },
            {
                "t_MJD": null,
                "t_disc": null,
                "dt_days": 35.86,
                "dt_years": 0.0982465753,
                "F_mJy": 4.62,
                "luminosity": 6.227182775e+40,
                "time": 35.86,
                "source": "unknown"
            },
            {
                "t_MJD": null,
                "t_disc": null,
                "dt_days": 50.65,
                "dt_years": 0.1387671233,
                "F_mJy": 4.84,
                "luminosity": 6.523715288e+40,
                "time": 50.65,
                "source": "unknown"
            },
            {
                "t_MJD": null,
                "t_disc": null,
                "dt_days": 67.61,
                "dt_years": 0.1852328767,
                "F_mJy": 5.86,
                "luminosity": 7.898547849e+40,
                "time": 67.61,
                "source": "unknown"
            },
            {
                "t_MJD": null,
                "t_disc": null,
                "dt_days": 94.64,
                "dt_years": 0.2592876712,
                "F_mJy": 9.06,
                "luminosity": 1.221174804e+41,
                "time": 94.64,
                "source": "unknown"
            },
            {
                "t_MJD": null,
                "t_disc": null,
                "dt_days": 111.62,
                "dt_years": 0.3058082192,
                "F_mJy": 9.1,
                "luminosity": 1.226566304e+41,
                "time": 111.62,
                "source": "unknown"
            },
            {
                "t_MJD": null,
                "t_disc": null,
                "dt_days": 126.51,
                "dt_years": 0.3466027397,
                "F_mJy": 9.1,
                "luminosity": 1.226566304e+41,
                "time": 126.51,
                "source": "unknown"
            },
            {
                "t_MJD": null,
                "t_disc": null,
                "dt_days": 143.62,
                "dt_years": 0.3934794521,
                "F_mJy": 11.71,
                "luminosity": 1.578361695e+41,
                "time": 143.62,
                "source": "unknown"
            },
            {
                "t_MJD": null,
                "t_disc": null,
                "dt_days": 164.38,
                "dt_years": 0.4503561644,
                "F_mJy": 12.93,
                "luminosity": 1.742802452e+41,
                "time": 164.38,
                "source": "unknown"
            },
            {
                "t_MJD": null,
                "t_disc": null,
                "dt_days": 174.47,
                "dt_years": 0.478,
                "F_mJy": 12.83,
                "luminosity": 1.729323701e+41,
                "time": 174.47,
                "source": "unknown"
            },
            {
                "t_MJD": null,
                "t_disc": null,
                "dt_days": 197.41,
                "dt_years": 0.5408493151,
                "F_mJy": 13.29,
                "luminosity": 1.791325954e+41,
                "time": 197.41,
                "source": "unknown"
            },
            {
                "t_MJD": null,
                "t_disc": null,
                "dt_days": 213.32,
                "dt_years": 0.5844383562,
                "F_mJy": 12.43,
                "luminosity": 1.675408699e+41,
                "time": 213.32,
                "source": "unknown"
            },
            {
                "t_MJD": null,
                "t_disc": null,
                "dt_days": 245.23,
                "dt_years": 0.6718630137,
                "F_mJy": 12.17,
                "luminosity": 1.640363947e+41,
                "time": 245.23,
                "source": "unknown"
            },
            {
                "t_MJD": null,
                "t_disc": null,
                "dt_days": 302.95,
                "dt_years": 0.83,
                "F_mJy": 12.05,
                "luminosity": 1.624189447e+41,
                "time": 302.95,
                "source": "unknown"
            },
            {
                "t_MJD": null,
                "t_disc": null,
                "dt_days": 383.92,
                "dt_years": 1.0518356164,
                "F_mJy": 12.24,
                "luminosity": 1.649799073e+41,
                "time": 383.92,
                "source": "unknown"
            },
            {
                "t_MJD": null,
                "t_disc": null,
                "dt_days": 453.66,
                "dt_years": 1.2429041096,
                "F_mJy": 11.12,
                "luminosity": 1.498837066e+41,
                "time": 453.66,
                "source": "unknown"
            },
            {
                "t_MJD": null,
                "t_disc": null,
                "dt_days": 582.31,
                "dt_years": 1.595369863,
                "F_mJy": 8.9,
                "luminosity": 1.199608803e+41,
                "time": 582.31,
                "source": "unknown"
            },
            {
                "t_MJD": null,
                "t_disc": null,
                "dt_days": 645.0,
                "dt_years": 1.7671232877,
                "F_mJy": 8.24,
                "luminosity": 1.110649049e+41,
                "time": 645.0,
                "source": "unknown"
            },
            {
                "t_MJD": null,
                "t_disc": null,
                "dt_days": 651.1,
                "dt_years": 1.7838356164,
                "F_mJy": 8.63,
                "luminosity": 1.163216176e+41,
                "time": 651.1,
                "source": "unknown"
            },
            {
                "t_MJD": null,
                "t_disc": null,
                "dt_days": 787.6,
                "dt_years": 2.1578082192,
                "F_mJy": 6.23,
                "luminosity": 8.397261621e+40,
                "time": 787.6,
                "source": "unknown"
            },
            {
                "t_MJD": null,
                "t_disc": null,
                "dt_days": 1032.0,
                "dt_years": 2.8273972603,
                "F_mJy": 4.21,
                "luminosity": 5.674554e+40,
                "time": 1032.0,
		"source": "unknown"
            },
            {
                "t_MJD": null,
                "t_disc": null,
                "dt_days": 1105.0,
                "dt_years": 3.0273972603,
                "F_mJy": 3.52,
                "luminosity": 4.744520209e+40,
                "time": 1105.0,
                "source": "unknown"
            },
            {
                "t_MJD": null,
                "t_disc": null,
                "dt_days": 1373.0,
                "dt_years": 3.7616438356,
                "F_mJy": 2.34,
                "luminosity": 3.154027639e+40,
                "time": 1373.0,
                "source": "unknown"
            },
            {
                "t_MJD": null,
                "t_disc": null,
                "dt_days": 1894.0,
                "dt_years": 5.1890410959,
                "F_mJy": 1.47,
                "luminosity": 1.981376337e+40,
                "time": 1894.0,
                "source": "unknown"
            }
        ]
    }
}]
